omoospace/__init__.py
omoospace/commands.py
omoospace/common.py
omoospace/functions.py
omoospace/items.py
omoospace/language.py
omoospace/omoospace.py
omoospace/pyperclip.py
omoospace/utils.py
omoospace/validators.py
omoospace-0.2.5.dist-info/WHEEL
omoospace-0.2.5.dist-info/entry_points.txt
omoospace-0.2.5.dist-info/METADATA
omoospace-0.2.5.dist-info/RECORD
