Metadata-Version: 2.3
Name: omoospace
Version: 0.2.5
Summary: 
Author: manan
Author-email: manan <icrdr2010@outlook.com>
Requires-Dist: ruamel-yaml>=0.17.35,<0.18
Requires-Dist: pypinyin>=0.49.0,<0.50
Requires-Dist: nutree>=0.5.1,<0.6
Requires-Dist: typer>=0.20.1 ; extra == 'cli'
Requires-Dist: inquirerpy>=0.3.4 ; extra == 'cli'
Requires-Python: >=3.10, <4
Provides-Extra: cli
